artd_siigo/__init__.py
artd_siigo/apps.py
artd_siigo/admin/__init__.py
artd_siigo/admin/base.py
artd_siigo/admin/bills.py
artd_siigo/admin/catalogs.py
artd_siigo/admin/configs.py
artd_siigo/admin/customers.py
artd_siigo/admin/import_progress.py
artd_siigo/admin/mapping.py
artd_siigo/admin/products.py
artd_siigo/data/__init__.py
artd_siigo/data/customer.py
artd_siigo/data/mapping.py
artd_siigo/data/product.py
artd_siigo/data/siigo_example_data.py
artd_siigo/data/source.py
artd_siigo/management/__init__.py
artd_siigo/management/commands/__init__.py
artd_siigo/management/commands/create_unique_fiscal_responsibilities.py
artd_siigo/management/commands/import_account_groups_from_siigo.py
artd_siigo/management/commands/import_cost_center_from_siigo.py
artd_siigo/management/commands/import_customers_from_siigo.py
artd_siigo/management/commands/import_document_types_from_siigo.py
artd_siigo/management/commands/import_fixed_assets_from_siigo.py
artd_siigo/management/commands/import_payment_types_from_siigo.py
artd_siigo/management/commands/import_price_lists_from_siigo.py
artd_siigo/management/commands/import_product_types_from_siigo.py
artd_siigo/management/commands/import_products_from_siigo.py
artd_siigo/management/commands/import_taxes_from_siigo.py
artd_siigo/management/commands/import_users_from_siigo.py
artd_siigo/management/commands/import_warehouses_from_siigo.py
artd_siigo/management/commands/map_locations.py
artd_siigo/management/commands/populate_customer_document_types.py
artd_siigo/management/commands/populate_customer_person_types.py
artd_siigo/management/commands/populate_customer_types.py
artd_siigo/migrations/0001_initial.py
artd_siigo/migrations/0002_rename_pricelist_siigopricelist_and_more.py
artd_siigo/migrations/0003_siigopricelist_json_data.py
artd_siigo/migrations/0004_warehouse.py
artd_siigo/migrations/0005_rename_warehouse_siigowarehouse_and_more.py
artd_siigo/migrations/0006_siigouser.py
artd_siigo-1.1.3.dist-info/LICENSE
artd_siigo-1.1.3.dist-info/METADATA
artd_siigo-1.1.3.dist-info/WHEEL
artd_siigo-1.1.3.dist-info/top_level.txt
artd_siigo-1.1.3.dist-info/RECORD
