Metadata-Version: 2.1
Name: artd_siigo
Version: 1.1.3
Summary: ArtD SIIGO.
Home-page: https://www.artd.com.co/
Author: Jonathan Urzola
Author-email: jonathan@artd.com.co
License: BSD-3-Clause
Classifier: Environment :: Web Environment
Classifier: Framework :: Django
Classifier: Intended Audience :: Developers
Classifier: License :: OSI Approved :: BSD License
Classifier: Operating System :: OS Independent
Classifier: Programming Language :: Python
Classifier: Programming Language :: Python :: 3
Classifier: Programming Language :: Python :: 3 :: Only
Classifier: Programming Language :: Python :: 3.6
Classifier: Programming Language :: Python :: 3.7
Classifier: Programming Language :: Python :: 3.8
Classifier: Programming Language :: Python :: 3.9
Classifier: Programming Language :: Python :: 3.10
Classifier: Programming Language :: Python :: 3.11
Classifier: Programming Language :: Python :: 3.12
Classifier: Topic :: Internet :: WWW/HTTP
Classifier: Topic :: Internet :: WWW/HTTP :: Dynamic Content
License-File: LICENSE
Requires-Dist: Django>=4.2.10
Requires-Dist: artd-customer>=1.0.17
Requires-Dist: artd-location>=1.0.6
Requires-Dist: artd-modules>=1.0.6
Requires-Dist: artd-order>=1.0.12
Requires-Dist: artd-partner>=1.0.13
Requires-Dist: artd-product>=1.0.22
Requires-Dist: artd-service>=1.0.8
Requires-Dist: artd-stock>=1.0.9
Requires-Dist: artd-urls>=1.0.6
Requires-Dist: artd-price-list>=1.0.13
Requires-Dist: artd-promotion>=1.0.17
Requires-Dist: asgiref>=3.8.1
Requires-Dist: asttokens>=2.4.1
Requires-Dist: backports.tarfile>=1.2.0
Requires-Dist: black>=24.8.0
Requires-Dist: certifi>=2024.8.30
Requires-Dist: cffi>=1.17.1
Requires-Dist: charset-normalizer>=3.3.2
Requires-Dist: click>=8.1.7
Requires-Dist: cryptography>=43.0.1
Requires-Dist: decorator>=5.1.1
Requires-Dist: django-admin>=2.0.2
Requires-Dist: django-autocomplete-light>=3.11.0
Requires-Dist: django-excel-response2>=3.0.6
Requires-Dist: django-extensions>=3.2.3
Requires-Dist: django-json-widget>=2.0.1
Requires-Dist: django-six>=1.0.5
Requires-Dist: docutils>=0.21.2
Requires-Dist: excel-base>=1.0.4
Requires-Dist: exceptiongroup>=1.2.2
Requires-Dist: executing>=2.1.0
Requires-Dist: idna>=3.10
Requires-Dist: importlib-metadata>=8.5.0
Requires-Dist: ipython>=8.28.0
Requires-Dist: isoweek>=1.3.3
Requires-Dist: jaraco.classes>=3.4.0
Requires-Dist: jaraco.context>=6.0.1
Requires-Dist: jaraco.functools>=4.1.0
Requires-Dist: jedi>=0.19.1
Requires-Dist: jeepney>=0.8.0
Requires-Dist: keyring>=25.4.1
Requires-Dist: markdown-it-py>=3.0.0
Requires-Dist: matplotlib-inline>=0.1.7
Requires-Dist: mdurl>=0.1.2
Requires-Dist: more-itertools>=10.5.0
Requires-Dist: mypy-extensions>=1.0.0
Requires-Dist: nh3>=0.2.18
Requires-Dist: packaging>=24.1
Requires-Dist: parso>=0.8.4
Requires-Dist: pathspec>=0.12.1
Requires-Dist: pexpect>=4.9.0
Requires-Dist: pillow>=10.4.0
Requires-Dist: pkginfo>=1.10.0
Requires-Dist: platformdirs>=4.3.6
Requires-Dist: prompt-toolkit>=3.0.48
Requires-Dist: ptyprocess>=0.7.0
Requires-Dist: pure-eval>=0.2.3
Requires-Dist: pycparser>=2.22
Requires-Dist: Pygments>=2.18.0
Requires-Dist: python-dateutil>=2.9.0.post0
Requires-Dist: readme-renderer>=44.0
Requires-Dist: requests>=2.32.3
Requires-Dist: requests-toolbelt>=1.0.0
Requires-Dist: rfc3986>=2.0.0
Requires-Dist: rich>=13.9.2
Requires-Dist: screen>=1.0.1
Requires-Dist: SecretStorage>=3.3.3
Requires-Dist: six>=1.16.0
Requires-Dist: sqlparse>=0.5.1
Requires-Dist: stack-data>=0.6.3
Requires-Dist: TimeConvert>=3.0.13
Requires-Dist: tomli>=2.0.2
Requires-Dist: traitlets>=5.14.3
Requires-Dist: twine>=5.1.1
Requires-Dist: types-requests>=2.32.0.20240914
Requires-Dist: typing-extensions>=4.12.2
Requires-Dist: tzlocal>=5.2
Requires-Dist: urllib3>=2.2.3
Requires-Dist: wcwidth>=0.2.13
Requires-Dist: xlwt>=1.3.0
Requires-Dist: zipp>=3.20.2
